{
  "4chan": "4chan",
  "Facial Recognition": "Ansiktsgjenkjenning",
  "Ansiktsgjenkjenning": "Ansiktsgjenkjenning",
  "Archiving": "Arkivering",
  "Arkiv": "Arkivering",
  "Arkivering/uthenting": "Arkivering",
  "Beregne og finne mønstre": "Dataanalyse",
  "Betalingsmidler": "Betalingsmidler",
  "Blackbird": "Brukernavnsøk",
  "Bluesky": "Bluesky",
  "Brukerkontoer": "Brukerkontoer",
  "Clubhouse": "Clubhouse",
  "Data Organization & Analysis": "Dataorganisering og analyse",
  "Dataorganisering og analyse": "Dataorganisering og analyse",
  "Misc": "Diverse",
  "Discord": "Discord",
  "Email": "E-post",
  "Facebook": "Facebook",
  "Flight Tracking": "Flysporıng",
  "General Search": "Generelt søk",
  "Geolocation": "Geolokasjon",
  "Google": "Google",
  "Image Forensics": "Bildeforensikk",
  "Image Search": "Bildesøk",
  "Instagram": "Instagram",
  "Investigative Databases": "Etterforskningsdatabaser",
  "LinkedIn": "LinkedIn",
  "Maps & Satellites": "Kart og satellitter",
  "Messaging Apps": "Meldingsapper",
  "OSINT Tools": "OSINT-verktøy",
  "People Search": "Personsøk",
  "Reddit": "Reddit",
  "Scrapers": "Skrapere",
  "Ship Tracking": "Skipssporing",
  "Social Media": "Sosiale medier",
  "Telegram": "Telegram",
  "TikTok": "TikTok",
  "Twitter": "Twitter/X",
  "Vehicle Tracking": "Kjøretøysporing",
  "Video Tools": "Videoverktøy",
  "VK": "VK",
  "Website Analysis": "Nettstedanalyse",
  "WhatsApp": "WhatsApp",
  "YouTube": "YouTube"
}
